hkjournalist/__init__.py
hkjournalist/journalist.py
hkjournalist/configuration/code_block.tex
hkjournalist-0.0.8.dist-info/LICENSE
hkjournalist-0.0.8.dist-info/METADATA
hkjournalist-0.0.8.dist-info/WHEEL
hkjournalist-0.0.8.dist-info/top_level.txt
hkjournalist-0.0.8.dist-info/RECORD
