Metadata-Version: 2.1
Name: hkjournalist
Version: 0.0.8
Summary: Custom Auto Report Generator for Python Program
Home-page: https://github.com/li-xin-yi/HK-journalist
Author: Xinyi Li
Author-email: wolixinyi@gmail.com
License: UNKNOWN
Platform: UNKNOWN
Classifier: Programming Language :: Python :: 3
Classifier: License :: OSI Approved :: MIT License
Requires-Dist: tabulate
Requires-Dist: pandas
Requires-Dist: pandoc
Requires-Dist: matplotlib
